vercel/cache/__init__.py
vercel/cache/_logging.py
vercel/cache/aio.py
vercel/cache/cache_build.py
vercel/cache/cache_in_memory.py
vercel/cache/context.py
vercel/cache/decorator/__init__.py
vercel/cache/decorator/aio.py
vercel/cache/decorator/aio.pyi
vercel/cache/decorator/sync.py
vercel/cache/decorator/sync.pyi
vercel/cache/runtime_cache.py
vercel/cache/types.py
vercel/cache/utils.py
vercel_functions_cache-0.2.4.dist-info/WHEEL
vercel_functions_cache-0.2.4.dist-info/METADATA
vercel_functions_cache-0.2.4.dist-info/RECORD
