Metadata-Version: 2.4
Name: vercel-functions-cache
Version: 0.2.4
Author: AlphaKR93
Author-email: AlphaKR93 <dev@alpha93.kr>
License-Expression: MIT
Requires-Dist: httpx>=0.28.1
Requires-Python: >=3.10
Project-URL: Homepage, https://pypi.org/project/vercel-functions
